amzpy/__init__.py
amzpy/parser.py
amzpy/scraper.py
amzpy/session.py
amzpy/utils.py
tests/__init__.py
tests/test_scraper.py
amzpy-0.2.1.dist-info/METADATA
amzpy-0.2.1.dist-info/WHEEL
amzpy-0.2.1.dist-info/top_level.txt
amzpy-0.2.1.dist-info/RECORD
